odoo/addons/l10n_es_atc_mod420/README.rst
odoo/addons/l10n_es_atc_mod420/__init__.py
odoo/addons/l10n_es_atc_mod420/__manifest__.py
odoo/addons/l10n_es_atc_mod420/data/l10n.es.aeat.map.tax.csv
odoo/addons/l10n_es_atc_mod420/data/l10n.es.aeat.map.tax.line.account.csv
odoo/addons/l10n_es_atc_mod420/data/l10n.es.aeat.map.tax.line.csv
odoo/addons/l10n_es_atc_mod420/data/l10n.es.aeat.map.tax.line.tax.csv
odoo/addons/l10n_es_atc_mod420/docs/420.pdf
odoo/addons/l10n_es_atc_mod420/docs/boe-modelo-420-quipu-descargar.pdf
odoo/addons/l10n_es_atc_mod420/i18n/es.po
odoo/addons/l10n_es_atc_mod420/i18n/l10n_es_atc_mod420.pot
odoo/addons/l10n_es_atc_mod420/models/__init__.py
odoo/addons/l10n_es_atc_mod420/models/mod420.py
odoo/addons/l10n_es_atc_mod420/readme/CONTRIBUTORS.md
odoo/addons/l10n_es_atc_mod420/readme/DESCRIPTION.md
odoo/addons/l10n_es_atc_mod420/readme/INSTALL.md
odoo/addons/l10n_es_atc_mod420/readme/ROADMAP.md
odoo/addons/l10n_es_atc_mod420/readme/USAGE.md
odoo/addons/l10n_es_atc_mod420/reports/Presentacion-420-XMLSchema.xsd
odoo/addons/l10n_es_atc_mod420/reports/mod420_report.xml
odoo/addons/l10n_es_atc_mod420/security/ir.model.access.csv
odoo/addons/l10n_es_atc_mod420/security/l10n_es_atc_mod420_security.xml
odoo/addons/l10n_es_atc_mod420/static/description/icon.png
odoo/addons/l10n_es_atc_mod420/static/description/index.html
odoo/addons/l10n_es_atc_mod420/static/src/pdf/caratula_sobre_420.pdf
odoo/addons/l10n_es_atc_mod420/tests/__init__.py
odoo/addons/l10n_es_atc_mod420/tests/test_l10n_es_atc_mod420.py
odoo/addons/l10n_es_atc_mod420/views/mod420_view.xml
odoo_addon_l10n_es_atc_mod420-18.0.1.0.5.dist-info/METADATA
odoo_addon_l10n_es_atc_mod420-18.0.1.0.5.dist-info/WHEEL
odoo_addon_l10n_es_atc_mod420-18.0.1.0.5.dist-info/top_level.txt
odoo_addon_l10n_es_atc_mod420-18.0.1.0.5.dist-info/RECORD
