Metadata-Version: 2.1
Name: odoo-addon-l10n_es_atc_mod420
Version: 18.0.1.0.5
Requires-Python: >=3.10
Requires-Dist: odoo-addon-base_location==18.0.*
Requires-Dist: odoo-addon-l10n_es_aeat==18.0.*
Requires-Dist: odoo-addon-l10n_es_atc==18.0.*
Requires-Dist: odoo-addon-report_xml==18.0.*
Requires-Dist: odoo==18.0.*
Summary: ATC Modelo 420
Home-page: https://github.com/OCA/l10n-spain
License: AGPL-3
Author: Binhex, Tecnativa, Odoo Community Association (OCA)
Author-email: support@odoo-community.org
Classifier: Programming Language :: Python
Classifier: Framework :: Odoo
Classifier: Framework :: Odoo :: 18.0
Classifier: License :: OSI Approved :: GNU Affero General Public License v3
